{
  "id": "esignet-local-env",
  "name": "eSignet (local)",
  "values": [
    { "key": "baseUrl", "value": "http://127.0.0.1:8080", "enabled": true, "description": "Must match MOSIP_ESIGNET_HOST when starting the server" },
    { "key": "applicationId", "value": "decl-app-1", "enabled": true },
    { "key": "otpApplicationId", "value": "partnernameforautomationesi-372269", "enabled": true },
    { "key": "clientId", "value": "decl-jwt-client-1", "enabled": true, "description": "Confidential OAuth client (private_key_jwt only). Registered by folder 2 Register OAuth client." },
    { "key": "clientJwk", "value": "", "enabled": true, "type": "secret", "description": "RSA private JWK JSON for folders 2 and 4 (must include kid, n, e, d). Run ./make.sh smoke-jwt-key and paste scripts/fixtures/smoke-jwt-client.jwk.json" },
    { "key": "otpClientJwk", "value": "", "enabled": true, "type": "secret", "description": "RSA private JWK JSON for otpClientId (folder 3, private_key_jwt); must match registered JWKS" },
    { "key": "otpClientId", "value": "I6eXdnnLGGj2A2BcTL-jug_0ujpnQXlBpKAbBCkGWEM", "enabled": true },
    { "key": "individualId", "value": "2760459465", "enabled": true },
    { "key": "otp", "value": "111111", "enabled": true },
    { "key": "redirectUri", "value": "https://localhost:3000", "enabled": true },
    { "key": "scope", "value": "openid profile email", "enabled": true },
    { "key": "username", "value": "decl-user-1", "enabled": true },
    { "key": "password", "value": "TempPassword123!", "enabled": true },
    { "key": "ouId", "value": "decl-ou-1", "enabled": true },
    { "key": "rpId", "value": "decl-ou-1", "enabled": true, "description": "Relying party id for client-mgmt create" },
    { "key": "clientMgmtToken", "value": "", "enabled": true, "description": "Bearer JWT with client_mgmt scope; iss must match baseUrl and signature must validate against /.well-known/jwks.json" },
    { "key": "clientMgmtClientId", "value": "", "enabled": true, "description": "Set automatically by folder 4 Create request" },
    { "key": "clientMgmtRequestTime", "value": "", "enabled": true, "description": "Set automatically by folder 4 create/update requests" },
    { "key": "clientMgmtPublicKey", "value": "", "enabled": true, "description": "Set automatically by folder 4 Create request (public JWK JSON object)" },
    { "key": "oauthClientPublicKey", "value": "", "enabled": true, "description": "Set automatically by folder 2 Register OAuth client (public JWK derived from clientJwk)" },
    { "key": "executionId", "value": "", "enabled": true },
    { "key": "challengeToken", "value": "", "enabled": true },
    { "key": "actionRef", "value": "action_001", "enabled": true },
    { "key": "assertion", "value": "", "enabled": true },
    { "key": "authId", "value": "", "enabled": true },
    { "key": "codeVerifier", "value": "", "enabled": true },
    { "key": "codeChallenge", "value": "", "enabled": true },
    { "key": "authCode", "value": "", "enabled": true },
    { "key": "clientAssertion", "value": "", "enabled": true, "description": "Set automatically by Token pre-request script" },
    { "key": "accessToken", "value": "", "enabled": true },
    { "key": "idToken", "value": "", "enabled": true }
  ],
  "_postman_variable_scope": "environment"
}
